py4writers/__init__.py
py4writers/api/__init__.py
py4writers/api/api.py
py4writers/client/__init__.py
py4writers/client/aiohttp.py
py4writers/const.py
py4writers/exceptions.py
py4writers/parsers/__init__.py
py4writers/parsers/order_parser.py
py4writers/tools/__init__.py
py4writers/types/__init__.py
py4writers/types/models.py
py4writers/utils/__init__.py
py4writers/utils/rate_limiter.py
py4writers/utils/retry.py
py4writers-0.9.2.dist-info/METADATA
py4writers-0.9.2.dist-info/WHEEL
py4writers-0.9.2.dist-info/RECORD
