Metadata-Version: 2.3
Name: py4writers
Version: 0.9.2
Summary: Python library for 4writers.net automation
Author: socalmy
Author-email: sergeitoropov2003@gmail.com
Requires-Python: >=3.12,<4.0
Classifier: Programming Language :: Python :: 3
Classifier: Programming Language :: Python :: 3.12
Classifier: Programming Language :: Python :: 3.13
Requires-Dist: aiohttp (>=3.11.10,<4.0.0)
Requires-Dist: bs4 (>=0.0.2,<0.0.3)
Requires-Dist: build (>=1.2.2.post1,<2.0.0)
Requires-Dist: certifi (>=2024.8.30,<2025.0.0)
Requires-Dist: envparse (>=0.2.0,<0.3.0)
Requires-Dist: lxml (>=5.3.0,<6.0.0)
Requires-Dist: setuptools (>=75.7.0,<76.0.0)
